{
  "name": "simple-colors",
  "description": "A LRN element",
  "main": "simple-colors.html",
  "dependencies": {
    "polymer": "Polymer/polymer#^1.10.1",
    "iron-icons": "PolymerElements/iron-icons#^2.1.1"
  },
  "devDependencies": {
    "iron-component-page": "PolymerElements/iron-component-page#^1.0.0",
    "iron-demo-helpers": "PolymerElements/iron-demo-helpers#^1.0.0",
    "web-component-tester": "^4.0.0",
    "webcomponentsjs": "webcomponents/webcomponentsjs#^0.7.0"
  },
  "homepage": "https://github.com/LRNWebComponents/simple-colors",
  "version": "1.0.5",
  "_release": "1.0.5",
  "_resolution": {
    "type": "version",
    "tag": "1.0.5",
    "commit": "2281a4f5aeb5ba7109c60c5463213cd824fc4989"
  },
  "_source": "https://github.com/LRNWebComponents/simple-colors.git",
  "_target": "^1.0.5",
  "_originalSource": "LRNWebComponents/simple-colors"
}